uwebserver/__init__.py
uwebserver/py.typed
uwebserver-0.3.2.dist-info/LICENSE
uwebserver-0.3.2.dist-info/METADATA
uwebserver-0.3.2.dist-info/WHEEL
uwebserver-0.3.2.dist-info/top_level.txt
uwebserver-0.3.2.dist-info/RECORD
