Metadata-Version: 2.1
Name: uwebserver
Version: 0.3.2
Summary: Simple web server for micropython
Author: jykob
License: MIT License
Project-URL: repository, https://github.com/jykob/uWebServer
Classifier: Development Status :: 4 - Beta
Classifier: Framework :: AsyncIO
Classifier: License :: OSI Approved :: MIT License
Classifier: Operating System :: OS Independent
Classifier: Programming Language :: Python :: 3
Classifier: Programming Language :: Python :: 3 :: Only
Classifier: Programming Language :: Python :: 3.10
Requires-Python: >=3.10
License-File: LICENSE
Provides-Extra: dev
Requires-Dist: ruff >=0.4.4 ; extra == 'dev'
Requires-Dist: pyright >=1.1.362 ; extra == 'dev'
